dbase3_py/__init__.py
dbase3_py/__main__.py
dbase3_py/dbase3.py
dbase3_py/dbfview.py
dbase3_py/test.py
dbase3_py/utils.py
dbase3_py-1.8.11.dist-info/LICENSE
dbase3_py-1.8.11.dist-info/METADATA
dbase3_py-1.8.11.dist-info/WHEEL
dbase3_py-1.8.11.dist-info/entry_points.txt
dbase3_py-1.8.11.dist-info/top_level.txt
dbase3_py-1.8.11.dist-info/RECORD
