Metadata-Version: 2.1
Name: dbase3-py
Version: 1.8.11
Summary: A Python library to manipulate DBase III database files
Home-page: https://github.com/sandy98/dbase3-py
Author: Domingo E. Savoretti
Author-email: esavoretti@gmail.com
License: UNKNOWN
Platform: UNKNOWN
Classifier: Programming Language :: Python :: 3
Classifier: License :: OSI Approved :: MIT License
Classifier: Operating System :: OS Independent
Requires-Python: >=3.6
License-File: LICENSE
